{
  "person": [
    {
      "id": "SRISHTI0002389772BLJTI",
      "name": "Arnab Mondal",
      "gender": "Male",
      "password": "Arnab@8016",
      "email": "arnabmondal203@gmail.com"
    },
    {
      "id": "SRISHTI0002330319JKTIE",
      "name": "Arnab Mondal",
      "gender": "Male",
      "password": "Arnab@8016",
      "email": "arnabmondal203@gmail.com"
    },
    {
      "id": "SRISHTI0002335111YZDII",
      "name": "Arnab Mondal",
      "gender": "Male",
      "password": "Arnab@8016",
      "email": "arnabmondal203@gmail.com"
    },
    {
      "id": "SRISHTI0002313189PQOMM",
      "name": "Arnab Mondal",
      "gender": "Male",
      "password": "Arnab@8016",
      "email": "arnabmondal203@gmail.com"
    },
    {
      "id": "SRISHTI0002376300KMCML",
      "name": "archana mondal",
      "gender": "Female",
      "password": "123",
      "email": "arnadmondal203@gmail.com"
    },
    {
      "id": "SRISHTI0002378832VAVUM",
      "name": "Archana Mondal",
      "gender": "Female",
      "password": "Arcg",
      "email": "arnab"
    },
    {
      "id": "SRISHTI0002394158LIMBZ",
      "name": "Archana Mondal",
      "gender": "Female",
      "password": "Arnab@8016",
      "email": "arnabmondal203@gmail.com"
    },
    {
      "id": "SRISHTI0002372630PQKLT",
      "name": "Archana Mondal",
      "gender": "Female",
      "password": "123",
      "email": "arnabmondal203@gmail.com"
    },
    {
      "id": "SRISHTI0002384520RGHLZ",
      "name": "Arnab Mondal",
      "gender": "Male",
      "password": "Arnab@8016",
      "email": "arnabmondal203@gmail.com"
    },
    {
      "id": "SRISHTI0002324706GGGFN",
      "name": "asd",
      "gender": "Male",
      "password": "2121",
      "email": "arnabmondal203@gmail.com"
    },
    {
      "id": "SRISHTI0002378034AIDAI",
      "name": "Arnab Mondal",
      "gender": "Male",
      "password": "Arnab@8016",
      "email": "arnabmondal203@gmail.com"
    },
    {
      "id": "SRISHTI0002347979JJFGM",
      "name": "ASHISH MANDI",
      "gender": "Male",
      "password": "qwerty",
      "email": "ashishmandi9085@gmail.com"
    },
    {
      "id": "SRISHTI0002337628IRQNY",
      "name": "aeafaasf",
      "gender": "Male",
      "password": "asfasf",
      "email": "arnabmondal203@gmail.com"
    },
    {
      "id": "SRISHTI0002322243SISAH",
      "name": "Arnab Mondal",
      "gender": "Male",
      "password": "Arnab@8016",
      "email": "arnabmondal203@gmail.com"
    },
    {
      "id": "SRISHTI0002364373PGVEW",
      "name": "Arnab",
      "gender": "Male",
      "password": "asdasd",
      "email": "arnabmondal203@gmail.com"
    },
    {
      "id": "SRISHTI0002308521RDKHP",
      "name": "Arnab Mondal",
      "gender": "Male",
      "password": "Arnab@8016",
      "email": "arnabmondal203@gmail.com"
    },
    {
      "id": "SRISHTI0002374669OFPSL",
      "name": "sdsdf",
      "gender": "Male",
      "password": "dsfsdf",
      "email": "dsfsdf"
    },
    {
      "id": "SRISHTI0002373613MEDNO",
      "name": "Arnab Mondal",
      "gender": "Male",
      "password": "Arnab@8016",
      "email": "arnabmondal203@gmail.com"
    },
    {
      "id": "SRISHTI0002377604CUNQK",
      "name": "Arnab Mondal",
      "gender": "Male",
      "password": "Arnab@8016",
      "email": "arnabmondal203@gmail.com"
    },
    {
      "id": "SRISHTI0002302525ARVVK",
      "name": "Arnab Mondal",
      "gender": "Male",
      "password": "Arnab@8016",
      "email": "arnabmondal203@gmail.com"
    },
    {
      "id": "SRISHTI0002384078QRKNF",
      "name": "Arnab Mondal",
      "gender": "Male",
      "password": "Arnab@8016",
      "email": "arnabmondal203@gmail.com"
    },
    {
      "id": "SRISHTI0002375346KGCWE",
      "name": "Archana Mondal",
      "gender": "Female",
      "password": "123456",
      "email": "arnabmondal203@gmail.com"
    },
    {
      "id": "SRISHTI0002348001BAQDZ",
      "name": "Archana Mondal",
      "gender": "Male",
      "password": "Arnab",
      "email": "arnabmondal203@gmail.com"
    },
    {
      "id": "SRISHTI0002346223NJWMX",
      "name": "Arnab Mondal",
      "gender": "Male",
      "password": "Arnab@8016",
      "email": "arnabmondal203@gmail.com"
    },
    {
      "id": "SRISHTI0002334401NPOBJ",
      "name": "Arnab Mondal",
      "gender": "Male",
      "password": "Arnab@8016",
      "email": "arnabmondal203@gmail.com"
    },
    {
      "id": "SRISHTI0002388053JFMBB",
      "name": "Archana Mondal",
      "gender": "Female",
      "password": "123456",
      "email": "arnabmondal203@gmail.com"
    },
    {
      "id": "SRISHTI0002301392YNAUB",
      "name": "Ashish Mandi",
      "gender": "Male",
      "password": "qwerty",
      "email": "ashishmandi9085@gmail.com"
    },
    {
      "id": "SRISHTI0002311494OWTEA",
      "name": "Tasir Ahhamed Laskar",
      "gender": "Male",
      "password": "viper",
      "email": "junaidahhamed78@gmail.com"
    }
  ]
}